{
    "id": "LESSON-001",
    "title": "Studio Lessons Learned",
    "documentType": "Permanent Studio Lessons Learned",
    "organization": "Two Marshalls Studios - Studio Operating System (TMS-OS)",
    "department": "Studio Governance",
    "category": "Lessons Learned",
    "owner": "Two Marshalls Studios",
    "status": "Verified",
    "version": "1.1",
    "created": "Historical recovery",
    "lastUpdated": "Work Session 086",
    "summary": "Provides the permanent structure for verified lessons learned aligned with the WS086 repository reconciliation.",
    "keywords": [
        "LESSON-001",
        "Studio Lessons Learned",
        "Studio Governance"
    ],
    "sections": [],
    "relatedDocuments": [
        "PROC-003",
        "STATE-001",
        "DOC-STATE-001",
        "DOC-INDEX-001",
        "WS-HIST-001",
        "DEC-LOG-001",
        "BUG-HIST-001",
        "TECH-DEBT-001",
        "ENH-LOG-001",
        "STD-001"
    ],
    "revisionHistory": [
        {
            "version": "1.0",
            "date": "Work Session 042",
            "summary": "Connected the verified permanent document to the shared structured Document Template Engine.",
            "status": "Verified"
        },
        {
            "version": "1.1",
            "date": "Work Session 086",
            "summary": "Reconciled lessons learned with the verified repository governance model.",
            "status": "Verified"
        }
    ],
    "verification": {
        "status": "Repository Reconciled",
        "verifiedBy": "Stephen Marshall",
        "method": "Reconciled against the verified v0.28.1 repository during Work Session 086."
    }
}